mortal_pip/__init__.py
mortal_pip/pip_main.pyd
mortal_pip/pip_main.so
mortal_pip-0.0.11.dist-info/METADATA
mortal_pip-0.0.11.dist-info/WHEEL
mortal_pip-0.0.11.dist-info/entry_points.txt
mortal_pip-0.0.11.dist-info/top_level.txt
mortal_pip-0.0.11.dist-info/RECORD
