Metadata-Version: 2.1
Name: mortal-pip
Version: 0.0.11
Summary: 'mortal工具集::pip'
Author: MJ
License: UNKNOWN
Platform: UNKNOWN
Classifier: Programming Language :: Python :: 3
Classifier: License :: OSI Approved :: MIT License
Classifier: Operating System :: OS Independent
Requires-Python: >=3.7
Requires-Dist: click>=8.0.0
